picfix-0.1.2.dist-info/METADATA
picfix-0.1.2.dist-info/WHEEL
picfix-0.1.2.dist-info/entry_points.txt
picfix-0.1.2.dist-info/licenses/LICENSE
picfix/__init__.py
picfix/__main__.py
picfix/cli.py
picfix/commands/__init__.py
picfix/commands/convert.py
picfix/commands/optimize.py
picfix/commands/resize.py
picfix/img_processors/__init__.py
picfix/img_processors/convert_processor.py
picfix/img_processors/optimize_processor.py
picfix/img_processors/resize_processor.py
picfix/logging.py
picfix/models/__init__.py
picfix/models/convert_model.py
picfix/models/optimize_model.py
picfix/models/resize_model.py
picfix-0.1.2.dist-info/RECORD
