Metadata-Version: 2.1
Name: picfix
Version: 0.1.2
Summary: Default template for PDM package
Author-Email: Hamza Y <letters2hamza@gmail.com>
License: MIT
Requires-Python: ==3.12.*
Requires-Dist: typer[all]>=0.12.3
Requires-Dist: Pillow>=10.4.0
Requires-Dist: loguru>=0.7.2
Requires-Dist: pydantic>=2.8.2
Requires-Dist: pytest>=8.3.2
